agentools/__init__.py
agentools/api/__init__.py
agentools/api/mocking.py
agentools/api/openai.py
agentools/assistants/__init__.py
agentools/assistants/chatgpt.py
agentools/assistants/core.py
agentools/assistants/realtime.py
agentools/assistants/structgpt.py
agentools/assistants/utils.py
agentools/messages/__init__.py
agentools/messages/content.py
agentools/messages/core.py
agentools/messages/realtime.py
agentools/retrieval/__init__.py
agentools/retrieval/db/__init__.py
agentools/retrieval/db/collection.py
agentools/retrieval/db/data.py
agentools/retrieval/db/embedding.py
agentools/tools/__init__.py
agentools/tools/core.py
agentools/tools/decorators/fail_with_message.py
agentools/tools/decorators/function_tool.py
agentools/tools/decorators/streaming_function_tool.py
agentools/tools/decorators/utils.py
agentools/tools/types.py
agentools/utils/tokens.py
agentools/utils/trackers.py
agentools-0.7.0.dist-info/METADATA
agentools-0.7.0.dist-info/WHEEL
agentools-0.7.0.dist-info/RECORD
