Metadata-Version: 2.3
Name: agentools
Version: 0.7.0
Summary: 
Author: Joong-Won Seo
Author-email: joong.won.seo@gmail.com
Requires-Python: >=3.10,<4.0
Classifier: Programming Language :: Python :: 3
Classifier: Programming Language :: Python :: 3.10
Classifier: Programming Language :: Python :: 3.11
Classifier: Programming Language :: Python :: 3.12
Classifier: Programming Language :: Python :: 3.13
Requires-Dist: docstring-parser (>=0.15,<0.16)
Requires-Dist: json-autocomplete (>=0.2,<0.3)
Requires-Dist: jsonref (>=1.1,<2.0)
Requires-Dist: jsonschema (>=4.20,<5.0)
Requires-Dist: openai[realtime] (>=1.61.0,<2.0.0)
Requires-Dist: pydantic (>=2.5,<3.0)
Requires-Dist: qdrant-client (>=1.9,<2.0)
Requires-Dist: tiktoken (>=0.7.0,<0.8.0)
Requires-Dist: typing-extensions (>=4.12.2,<5.0.0)
